<?xml version="1.0" encoding="utf-8"?>
<!--Supcan Freeform -->
<freeform>
<Properties bgColor="#e5eaff,#faffff">
</Properties>
<Fonts>
	<Font faceName="微软雅黑" size="-13" />
	<Font size="14" />
	<Font size="-16" bold="1"/>
</Fonts>
<Objects>
	<TableLayout width='100%' height='100%'>
	<col width='10'/>
	<col width='.1'/>
	<col width='10'/>
	<TR height='10'><TD/><TD/><TD/></TR>
	<TR height='.1'>
		<TD/>
		<TD>
			<Tab id="Tab1" BackColor="#e5eaff" spacing.top="0">
				<Component id="T" type="treelist" url="t1.xml" createPara="border=none" text="树列表"/>
				<Component id="Cht" type="chart" text="统计图" createPara="border=none"/>
				<Component id="R" type="report" url="../report/report1.xml" createPara="border=none" text="报表"/>
			</Tab>
		</TD>
		<TD/>
	</TR>
	<TR height='10'><TD/><TD/><TD/></TR>
	</TableLayout>
</Objects>
</freeform>